eventsourcing/__init__.py
eventsourcing/application.py
eventsourcing/cipher.py
eventsourcing/compressor.py
eventsourcing/cryptography.py
eventsourcing/dcb/__init__.py
eventsourcing/dcb/api.py
eventsourcing/dcb/application.py
eventsourcing/dcb/domain.py
eventsourcing/dcb/msgpack.py
eventsourcing/dcb/persistence.py
eventsourcing/dcb/popo.py
eventsourcing/dcb/postgres_tt.py
eventsourcing/dcb/tests.py
eventsourcing/dispatch.py
eventsourcing/domain.py
eventsourcing/interface.py
eventsourcing/persistence.py
eventsourcing/popo.py
eventsourcing/postgres.py
eventsourcing/projection.py
eventsourcing/py.typed
eventsourcing/sqlite.py
eventsourcing/system.py
eventsourcing/tests/__init__.py
eventsourcing/tests/application.py
eventsourcing/tests/domain.py
eventsourcing/tests/persistence.py
eventsourcing/tests/postgres_utils.py
eventsourcing/utils.py
eventsourcing-9.5.2.dist-info/METADATA
eventsourcing-9.5.2.dist-info/WHEEL
eventsourcing-9.5.2.dist-info/licenses/AUTHORS
eventsourcing-9.5.2.dist-info/licenses/LICENSE
eventsourcing-9.5.2.dist-info/RECORD
