Metadata-Version: 2.4
Name: eventsourcing
Version: 9.5.2
Summary: Event sourcing in Python
License-Expression: BSD-3-Clause
License-File: AUTHORS
License-File: LICENSE
Keywords: event sourcing,event store,domain driven design,domain-driven design,ddd,cqrs,cqs
Author: John Bywater
Author-email: john.bywater@appropriatesoftware.net
Requires-Python: >=3.10.0
Classifier: Development Status :: 5 - Production/Stable
Classifier: Intended Audience :: Developers
Classifier: Intended Audience :: Education
Classifier: Intended Audience :: Science/Research
Classifier: License :: OSI Approved :: BSD License
Classifier: Operating System :: OS Independent
Classifier: Programming Language :: Python :: 3
Classifier: Programming Language :: Python :: 3.10
Classifier: Programming Language :: Python :: 3.11
Classifier: Programming Language :: Python :: 3.12
Classifier: Programming Language :: Python :: 3.13
Classifier: Programming Language :: Python :: 3.14
Classifier: Programming Language :: Python
Classifier: Topic :: Software Development :: Libraries :: Python Modules
Provides-Extra: crypto
Provides-Extra: cryptography
Provides-Extra: postgres
Requires-Dist: cryptography (>=44.0) ; extra == "cryptography"
Requires-Dist: psycopg[pool] (>=3.2) ; extra == "postgres"
Requires-Dist: pycryptodome (>=3.22) ; extra == "crypto"
Requires-Dist: typing_extensions
Project-URL: Documentation, https://eventsourcing.readthedocs.io/
Project-URL: Homepage, https://github.com/pyeventsourcing/eventsourcing
Project-URL: Repository, https://github.com/pyeventsourcing/eventsourcing
